fgvcdata/__init__.py
fgvcdata/aircraft.py
fgvcdata/base.py
fgvcdata/birds.py
fgvcdata/cars.py
fgvcdata/dogs.py
fgvcdata/flowers.py
fgvcdata/icub.py
fgvcdata/data/cubplus_image_class_labels.txt
fgvcdata-0.1.0.dist-info/LICENSE
fgvcdata-0.1.0.dist-info/METADATA
fgvcdata-0.1.0.dist-info/WHEEL
fgvcdata-0.1.0.dist-info/top_level.txt
fgvcdata-0.1.0.dist-info/RECORD
