Metadata-Version: 2.1
Name: fgvcdata
Version: 0.1.0
Summary: Pytorch Datasets for Fine Grained Visual Classification using a common interface.
Home-page: https://github.com/catalys1/fgvc-data-pytorch
Author: Connor Anderson
Author-email: connor.anderson@byu.edu
License: MIT
Platform: UNKNOWN
Classifier: License :: OSI Approved :: MIT License
Classifier: Programming Language :: Python
Classifier: Programming Language :: Python :: 3
Classifier: Programming Language :: Python :: 3.6
Classifier: Programming Language :: Python :: Implementation :: CPython
Classifier: Programming Language :: Python :: Implementation :: PyPy
Requires-Python: >=3.6.0
Requires-Dist: pillow
Requires-Dist: scipy
Requires-Dist: torch
Requires-Dist: torchvision
